LICENSE
MANIFEST.in
README.rst
setup.cfg
setup.py
test-cert-only.py
test.py
apk_parse/__init__.py
apk_parse/androconf.py
apk_parse/apk.py
apk_parse/bytecode.py
apk_parse/dvm_permissions.py
apk_parse/util.py
apk_parse/zipfile.py
apk_parse_ph4.egg-info/PKG-INFO
apk_parse_ph4.egg-info/SOURCES.txt
apk_parse_ph4.egg-info/dependency_links.txt
apk_parse_ph4.egg-info/requires.txt
apk_parse_ph4.egg-info/top_level.txt