Metadata-Version: 1.1
Name: apk-parse-ph4
Version: 0.1.7
Summary: APK parsing tools
Home-page: https://github.com/ph4r05/apk_parse/
Author: Dusan Klinec ph4r05
Author-email: dusan.klinec@gmail.com
License: 
